setup.cfg
setup.py
LinconSerial.egg-info/PKG-INFO
LinconSerial.egg-info/SOURCES.txt
LinconSerial.egg-info/dependency_links.txt
LinconSerial.egg-info/top_level.txt
linconserial/__init__.py
linconserial/exceptions.py
linconserial/lincon.py
linconserial/scripts/__init__.py