Metadata-Version: 1.1
Name: LinconSerial
Version: 0.0.6
Summary: Linux Connect Over Serial
Home-page: https://bitbucket.org/sjennings/linconserial
Author: Sean Jennings
Author-email: seanrjennings@gmail.com
License: MIT
Download-URL: https://bitbucket.org/sjennings/linconserial/get/master.tar.gz
Platform: UNKNOWN
Classifier: Development Status :: 3 - Alpha
Classifier: Programming Language :: Python :: 2.7
